README.md
setup.py
auth0_login/__init__.py
auth0_login/config.py
auth0_login.egg-info/PKG-INFO
auth0_login.egg-info/SOURCES.txt
auth0_login.egg-info/dependency_links.txt
auth0_login.egg-info/entry_points.txt
auth0_login.egg-info/not-zip-safe
auth0_login.egg-info/requires.txt
auth0_login.egg-info/top_level.txt
auth0_login/aws/__init__.py
auth0_login/aws/__main__.py
auth0_login/aws/account.py
auth0_login/aws/console.py
auth0_login/aws/credentials.py
auth0_login/aws/saml_assertion.py
auth0_login/aws/sts_command.py
auth0_login/logging/__init__.py
auth0_login/logging/fatal.py
auth0_login/pkce/__init__.py
auth0_login/pkce/__main__.py
auth0_login/pkce/callback.py
auth0_login/pkce/command.py
auth0_login/saml/__init__.py
auth0_login/saml/__main__.py
auth0_login/saml/callback.py
auth0_login/saml/command.py
auth0_login/util/__init__.py
auth0_login/util/url.py