Metadata-Version: 1.2
Name: auth0-login
Version: 0.5.1
Summary: CLI to obtain JWT, SAML tokens, and AWS credentials using Auth0, OAuth and SAML
Home-page: https://github.com/binxio/auth0-login
Author: Mark van Holsteijn
Author-email: mark@binx.io
License: Apache Software License (http://www.apache.org/licenses/LICENSE-2.0)
Platform: any
Classifier: Development Status :: 3 - Alpha
Classifier: Environment :: Console
Classifier: Intended Audience :: Developers
Classifier: License :: OSI Approved :: Apache Software License
Classifier: Operating System :: POSIX
Classifier: Operating System :: MacOS
Classifier: Operating System :: Unix
Classifier: Operating System :: Microsoft :: Windows
Classifier: Programming Language :: Python :: 3
Classifier: Topic :: Software Development :: Libraries :: Python Modules
Requires-Python: >=3.6
